apnet_pt/__init__.py
apnet_pt/atomic_datasets.py
apnet_pt/classical_induction.py
apnet_pt/constants.py
apnet_pt/layers.py
apnet_pt/multipole.py
apnet_pt/pairwise_datasets.py
apnet_pt/pretrained_models.py
apnet_pt/pytorch_atom_model.py
apnet_pt/torch_util.py
apnet_pt/util.py
apnet_pt/AtomModels/__init__.py
apnet_pt/AtomModels/ap2_atom_model.py
apnet_pt/AtomModels/ap3_atom_model.py
apnet_pt/AtomPairwiseModels/__init__.py
apnet_pt/AtomPairwiseModels/apnet2.py
apnet_pt/AtomPairwiseModels/apnet2_fused.py
apnet_pt/AtomPairwiseModels/apnet3.py
apnet_pt/AtomPairwiseModels/dapnet2.py
apnet_pt/AtomPairwiseModels/mtp_mtp.py
apnet_pt/data/vdw-params.csv
apnet_pt/models/am_ensemble/am_0.pt
apnet_pt/models/am_ensemble/am_1.pt
apnet_pt/models/am_ensemble/am_2.pt
apnet_pt/models/am_ensemble/am_3.pt
apnet_pt/models/am_ensemble/am_4.pt
apnet_pt/models/ap2-fused_ensemble/ap2_1.pt
apnet_pt/models/ap2-fused_ensemble/ap2_2.pt
apnet_pt/models/ap2-fused_ensemble/ap2_3.pt
apnet_pt/models/ap2-fused_ensemble/ap2_4.pt
apnet_pt/models/dapnet2/B2PLYP-D3aug-cc-pVTZunCP_to_CCSD_LP_T_RP_CBSCP_0.pt
apnet_pt/models/dapnet2/B3LYP-D3aug-cc-pVTZunCP_to_CCSD_LP_T_RP_CBSCP_0.pt
apnet_pt/models/dapnet2/HFaug-cc-pVDZCP_to_CCSD_LP_T_RP_CBSCP_0.pt
apnet_pt/models/dapnet2/MP2aug-cc-pVTZCP_to_CCSD_LP_T_RP_CBSCP_0.pt
apnet_pt/models/dapnet2/SAPT0aug-cc-pVDZSA_to_CCSD_LP_T_RP_CBSCP_0.pt
apnet_pt/models/dapnet2/wB97X-Vaug-cc-pVTZCP_to_CCSD_LP_T_RP_CBSCP_0.pt
apnet_pt/pt_datasets/__init__.py
apnet_pt/pt_datasets/ap2_fused_ds.py
apnet_pt/pt_datasets/dapnet_ds.py
qcml_mcp/__init__.py
qcml_mcp/server.py
qcml_mcp/timings/__init__.py
qcml_mcp/timings/all_polynomial_fits.py
qcml_mcp/timings/estimate_timings.py
qcmlforge/__init__.py
qcmlforge/qca.py
qcmlforge-0.0.11.dist-info/licenses/LICENSE
qcmlforge-0.0.11.dist-info/METADATA
qcmlforge-0.0.11.dist-info/WHEEL
qcmlforge-0.0.11.dist-info/top_level.txt
qcmlforge-0.0.11.dist-info/zip-safe
qcmlforge-0.0.11.dist-info/RECORD
