Metadata-Version: 2.4
Name: qcmlforge
Version: 0.0.11
Summary: Package for creating QC ML models on QCArchive datasets. The AP-Net2 has been re-implemnented in PyTorch with newer versions to come.
Author-email: "Austin M. Wallace" <awallace43@gatech.edu>
License: MIT
Project-URL: Homepage, https://github.com/Awallace3/QCMLForge
Project-URL: Bug Tracker, https://github.com/Awallace3/QCMLForge/issues
Classifier: Programming Language :: Python :: 3
Classifier: Operating System :: OS Independent
Requires-Python: >=3.12
License-File: LICENSE
Requires-Dist: torch==2.7.0
Requires-Dist: qm_tools_aw
Requires-Dist: numpy>=2.2.0
Requires-Dist: qcelemental>=0.29.0
Requires-Dist: torch-geometric==2.6.1
Requires-Dist: torch-scatter==2.1.2
Requires-Dist: pytorch-minimize
Requires-Dist: qcportal>=0.59
Dynamic: license-file
